stav/__init__.py
stav/eu/__init__.py
stav/eu/aia/__init__.py
stav-0.1.dist-info/LICENSE.txt
stav-0.1.dist-info/METADATA
stav-0.1.dist-info/WHEEL
stav-0.1.dist-info/top_level.txt
stav-0.1.dist-info/RECORD
