Metadata-Version: 2.1
Name: stav
Version: 0.1
Summary: STAV: System Trustworthiness and Accountability Vocabulary
Home-page: https://github.com/bact/stav
Author: Arthit Suriyawongkul
Author-email: suriyawa@tcd.ie
License: MIT
Project-URL: Source Code, https://github.com/bact/stav
Project-URL: Bug Tracker, https://github.com/bact/stav/issues
Keywords: accountability,trustworthiness,artificial intelligence,documentation,law,regulations,vocabulary,ontology
Classifier: Development Status :: 1 - Planning
Classifier: Programming Language :: Python :: 3
Classifier: Intended Audience :: Developers
Classifier: Intended Audience :: Legal Industry
Classifier: License :: OSI Approved :: MIT License
Classifier: Topic :: Scientific/Engineering :: Artificial Intelligence
Classifier: Topic :: Software Development :: Documentation
Classifier: Topic :: System :: Software Distribution
Requires-Python: >=3
License-File: LICENSE.txt
